senapp/LICENSE
senapp/README.md
senapp/__init__.py
senapp/cli.py
senapp/log.py
senapp/shell.py
senapp-0.2.0.dist-info/METADATA
senapp-0.2.0.dist-info/WHEEL
senapp-0.2.0.dist-info/RECORD
