Metadata-Version: 2.1
Name: senapp
Version: 0.2.0
Summary: A Python 3 package for CLI app development.
Project-URL: Repository, https://github.com/senumehana/senapp
Author-email: Volodymyr Zakalyk <volodymyr.zakalyk@gmail.com>
Maintainer-email: Volodymyr Zakalyk <volodymyr.zakalyk@gmail.com>
License: MIT License
Keywords: cli,log,shell
Classifier: Development Status :: 3 - Alpha
Classifier: Intended Audience :: Developers
Classifier: License :: OSI Approved :: MIT License
Classifier: Operating System :: POSIX :: Linux
Classifier: Programming Language :: Python :: 3
Classifier: Programming Language :: Python :: 3.6
Classifier: Programming Language :: Python :: 3.7
Classifier: Programming Language :: Python :: 3.8
Classifier: Programming Language :: Python :: 3.9
Classifier: Programming Language :: Python :: 3.10
Classifier: Programming Language :: Python :: 3.11
Classifier: Topic :: Software Development
Requires-Python: >=3.6
